{"CFPlugInFactories":{"27174BC7-8D26-4EE2-8844-84C257FC3844":"DropboxPluginFactory"},"CFBundleIdentifier":"com.getdropbox.finderplugin","CFPlugInDynamicRegistration":"NO","CFBundleInfoDictionaryVersion":"6.0","CFBundleVersion":"169","CFBundleExecutable":"DropboxPlugin","CFPlugInUnloadFunction":"","CFPlugInTypes":{"2F6522E9-3E66-11D5-80A7-003065B300BC":["27174BC7-8D26-4EE2-8844-84C257FC3844"]},"CFBundleSignature":"Plug","CFPlugInDynamicRegisterFunction":"","CFBundlePackageType":"BNDL","CFBundleDevelopmentRegion":"English"}